odoo10_addon_mrp_flattened_bom_xlsx-10.0.1.0.0-py2.7-nspkg.pth
odoo/addons/mrp_flattened_bom_xlsx/README.rst
odoo/addons/mrp_flattened_bom_xlsx/__init__.py
odoo/addons/mrp_flattened_bom_xlsx/__manifest__.py
odoo/addons/mrp_flattened_bom_xlsx/models/__init__.py
odoo/addons/mrp_flattened_bom_xlsx/models/mrp_bom.py
odoo/addons/mrp_flattened_bom_xlsx/report/__init__.py
odoo/addons/mrp_flattened_bom_xlsx/report/flattened_bom_xlsx.py
odoo/addons/mrp_flattened_bom_xlsx/report/flattened_bom_xlsx.xml
odoo/addons/mrp_flattened_bom_xlsx/static/description/icon.png
odoo10_addon_mrp_flattened_bom_xlsx-10.0.1.0.0.dist-info/DESCRIPTION.rst
odoo10_addon_mrp_flattened_bom_xlsx-10.0.1.0.0.dist-info/METADATA
odoo10_addon_mrp_flattened_bom_xlsx-10.0.1.0.0.dist-info/RECORD
odoo10_addon_mrp_flattened_bom_xlsx-10.0.1.0.0.dist-info/WHEEL
odoo10_addon_mrp_flattened_bom_xlsx-10.0.1.0.0.dist-info/metadata.json
odoo10_addon_mrp_flattened_bom_xlsx-10.0.1.0.0.dist-info/namespace_packages.txt
odoo10_addon_mrp_flattened_bom_xlsx-10.0.1.0.0.dist-info/top_level.txt
